{"BP0/5njUv1LENqNslhLfFg==":"gibland-logo-trans-122x33.png","MLrr38QH6TAyKgar1nJ6ZQ==":"gibland-icon-trans-100x27.png","MIV8FcZUDUp/tpieWCMg7w==":"uhr-logo-trans-360x254.png","EJ10aN3J/m3CU8a41yLDOw==":"bg-1-1920x1080.jpg","YSzVkg3pqbB2PJU8cnjW/w==":"uhr-logo-trans-192x135.png","AFDvXfiZV0x7nNkSGVnBvw==":"gibland-logo-white-274x75.jpg","fND2Du5SzasUmzFtYKosPw==":"gibland-logo-trans-702x191.png","zuBuIHB+pGtsn90wqL6YmQ==":"uhr-logo-white-360x254.jpg","hov5ocXX7rd9pCSumhwLAQ==":"uhr-logo-trans-272x192.png","gyHgWpoaGVrObWt8vvzOGQ==":"uhr-siang-1920-1920x1229.jpg","7RtlrLph5jevqsBjqDe7LA==":"uhr%20siang%20untuk%20background-2000x1124.jpg","JKZxSMB4FVLasDG+Ue79Hg==":"uhr-siang-1366-1366x874.jpg","wr0GEJ2HbNcVBOu8VzwL2Q==":"uhr-siang-1367-1366x874.jpg","8rvwTqh/XzirceLcyA9umw==":"mbr-721x1080.jpg","RR4y0IDvuSkNntw5mNFK1g==":"siteplan-uhr-1168x850.jpg","pgiRvt9dqm+y4KjahbP42Q==":"7-1014x1014.jpg","JDYqOckoG0aL5I4tniqEUg==":"type%20studio%20(bedroom)-2000x1125.jpg","ZOwBJOsGcm3v7uNGlloIaA==":"6%20room%20lampu+sprinkle+exhaust-2000x1339.jpg","mCHzgWlPChxhMkuWEqRTRw==":"8-534x534.jpg","++IYTWAaAEuuohAM4OZBCA==":"9-534x534.jpg","O/agWQIdIzOMUdyk/FeoNQ==":"10-534x534.jpg","SfuikqxAbWPTXXz8DAYaTw==":"type%201br%20(livingroom)-2000x1125.jpg","wF34qwqlKMCc8oWDnwePeg==":"type%202br%20(livingroom)-2000x1125.jpg","cEd/WOGF8eyc8zKnL61tMA==":"gibland-logo-trans-534x145.png","sYjFddgcjxnt8vhf6Raedw==":"img-5507-2000x1500.jpg","BldwjU2hlEDA+kf/j9fn+w==":"24-security-480x480.png","BUsH/YE+8LWL1fjKU4bYvA==":"cable-tv-480x480.png","k3EtfjB1GJmP0hHS8t6s4g==":"fb-service-480x480.png","vIM4ZaOKBlh2BxyOsmpO2w==":"fingerprint-480x480.png","uNMhoK2Y6XQ2Hz54mhtT3w==":"gym-480x480.png","KbIq+KtRtaIhgozbAMQeow==":"jogging-track-480x480.png","khT1W9or4ma4jiZBCdQOHw==":"kindergarten-480x480.png","Cu+RtWXvgJ4AT1k4a/xzDQ==":"lagoon-pool-480x480.png","i2ILwnubVtpO5van6Ta4vg==":"medical-480x480.png","VRlUMcAINqgheQ9RgFpq6Q==":"playpark-480x480.png","Bg0QznW41PX+7BmCFI8xZQ==":"retail-commercial-480x480.png","D2jpB7UX3yG6yZOPJzOCkA==":"shuttle-480x480.png","k4FzE3UId5Wq1y9vJMrgZQ==":"sky-garden-480x480.png","+5KU7ovKFH3GA4XQrl9HnA==":"sky-lounge-480x480.png","fDj4HyidC7hXQTACodZYOA==":"spa-sauna-480x480.png","IgWY+jxMIeVOoGtUeWoK9g==":"urban-worlds-480x480.png","nJrug9ZSZcReWWuhayfz1g==":"worship-480x480.png","y1dB/85USuYS8zZImkWcTQ==":"gibland-logo-trans-720x196.png","CxhrNCfRoxr5oykehOydvA==":"realestate%20indonesia2-436x289.jpg"}